fluo/__init__.py
fluo/fitter.py
fluo/models.py
fluo/simulation.py
fluo/statistics.py
fluo/utils.py
fluo-1.1.dist-info/LICENSE
fluo-1.1.dist-info/METADATA
fluo-1.1.dist-info/WHEEL
fluo-1.1.dist-info/top_level.txt
fluo-1.1.dist-info/RECORD
