Metadata-Version: 2.1
Name: fluo
Version: 1.1
Summary: Fluorescence in time domain toolkit.
Home-page: https://github.com/AnnaChmielinska/fluo
Author: Anna Chmielinska
Author-email: anka.chmielinska@gmail.com
License: General Public License 3
Download-URL: https://github.com/AnnaChmielinska/fluo/archive/1.1.tar.gz
Platform: UNKNOWN
License-File: LICENSE
Requires-Dist: matplotlib (<3.4.3,>=3.4.2)
Requires-Dist: lmfit (<1.0.3,>=1.0.2)
Requires-Dist: numdifftools (<0.9.41,>=0.9.40)
Requires-Dist: scipy (<1.7.1,>=1.7.0)
Requires-Dist: numpy (<1.21.1,>=1.21.0)
Requires-Dist: tqdm (<4.15.1,>=4.15.0)
Requires-Dist: importlib-metadata (<4.5.1,>=4.5.0)
